deepworm_algorithm/__init__.py
deepworm_algorithm/active_contour.py
deepworm_algorithm/edge_enhancing.py
deepworm_algorithm/find_roi.py
deepworm_algorithm/graph_cut.py
deepworm_algorithm/pixel_annotator.py
deepworm_algorithm/roi_finder.py
deepworm_algorithm/skeleton_extractor.py
deepworm_algorithm/straightener.py
deepworm_algorithm/utils/__init__.py
deepworm_algorithm/utils/geometry.py
deepworm_algorithm/utils/interpolate.py
deepworm_algorithm/utils/resample.py
deepworm_algorithm/utils/spline_geometry.py
deepworm_algorithm-0.1.11.dist-info/DESCRIPTION.rst
deepworm_algorithm-0.1.11.dist-info/METADATA
deepworm_algorithm-0.1.11.dist-info/RECORD
deepworm_algorithm-0.1.11.dist-info/WHEEL
deepworm_algorithm-0.1.11.dist-info/metadata.json
deepworm_algorithm-0.1.11.dist-info/top_level.txt
