Metadata-Version: 2.0
Name: deepworm-algorithm
Version: 0.1.11
Summary: A set of algorithms for analysing worm image
Home-page: http://www.deepdiy.net/
Author: JohnsonNie
Author-email: pubrcv@163.com
License: UNKNOWN
Platform: UNKNOWN
Classifier: Programming Language :: Python :: 3
Classifier: License :: OSI Approved :: MIT License
Classifier: Operating System :: OS Independent
Requires-Python: >=3.6
Requires-Dist: matplotlib
Requires-Dist: networkx
Requires-Dist: numpy
Requires-Dist: opencv-python
Requires-Dist: scikit-image
Requires-Dist: scipy
Requires-Dist: thinning-py3
